cloudnet_api_client/__init__.py
cloudnet_api_client/client.py
cloudnet_api_client/containers.py
cloudnet_api_client/dl.py
cloudnet_api_client/py.typed
cloudnet_api_client/utils.py
cloudnet_api_client/version.py
cloudnet_api_client-0.12.7.dist-info/METADATA
cloudnet_api_client-0.12.7.dist-info/WHEEL
cloudnet_api_client-0.12.7.dist-info/licenses/LICENSE
cloudnet_api_client-0.12.7.dist-info/RECORD
