Metadata-Version: 2.4
Name: cloudnet-api-client
Version: 0.12.7
Summary: Cloudnet API client
Author-email: Simo Tukiainen <simo.tukiainen@fmi.fi>
License-File: LICENSE
Classifier: Development Status :: 3 - Alpha
Classifier: Intended Audience :: Science/Research
Classifier: License :: OSI Approved :: MIT License
Classifier: Operating System :: OS Independent
Classifier: Programming Language :: Python :: 3
Classifier: Topic :: Scientific/Engineering :: Atmospheric Science
Requires-Python: >=3.10
Requires-Dist: aiohttp
Requires-Dist: numpy
Requires-Dist: requests
Requires-Dist: tqdm
Provides-Extra: dev
Requires-Dist: pre-commit; extra == 'dev'
Requires-Dist: release-version; extra == 'dev'
Requires-Dist: types-requests; extra == 'dev'
Requires-Dist: types-tqdm; extra == 'dev'
Provides-Extra: test
Requires-Dist: mypy; extra == 'test'
Requires-Dist: netcdf4; extra == 'test'
Requires-Dist: pytest; extra == 'test'
Requires-Dist: pytest-asyncio; extra == 'test'
